fastapi_route_logger_middleware/__init__.py
fastapi_route_logger_middleware-0.2.3.dist-info/LICENSE
fastapi_route_logger_middleware-0.2.3.dist-info/METADATA
fastapi_route_logger_middleware-0.2.3.dist-info/WHEEL
fastapi_route_logger_middleware-0.2.3.dist-info/top_level.txt
fastapi_route_logger_middleware-0.2.3.dist-info/RECORD
