Metadata-Version: 2.1
Name: fastapi-route-logger-middleware
Version: 0.2.3
Summary: Simple middleware for FastAPI to generate log entries on all requests
Home-page: https://github.com/jeffsiver/fastapi-route-logger
Author: Jeff Siver
Author-email: jeffsiver@gmail.com
License: UNKNOWN
Keywords: fastapi,logging,middleware
Platform: UNKNOWN
Classifier: Development Status :: 3 - Alpha
Classifier: Environment :: Web Environment
Classifier: Intended Audience :: Developers
Classifier: Topic :: Software Development :: Libraries :: Python Modules
Classifier: License :: OSI Approved :: MIT License
Classifier: Programming Language :: Python :: 3
Classifier: Programming Language :: Python :: 3.8
Classifier: Programming Language :: Python :: 3.9
Classifier: Programming Language :: Python :: 3.10
Classifier: Programming Language :: Python :: 3 :: Only
Requires-Python: >=3.7
License-File: LICENSE
Requires-Dist: fastapi
